[
    "===============================================================================",
    "Canonical reaction for GLYCOLALDEHYDE[c] sink in biocyc representative database.",
    {
        "id": "ALDEHYDE-DEHYDROGENASE-NADP+-RXN-GLYCOLALDEHYDE/NADP/WATER//GLYCOLATE/NADPH/PROTON",
        "name": "",
        "subsystem": "",
        "lower_bound": 0,
        "upper_bound": 1000.0,
        "metabolites": {
            "GLYCOLALDEHYDE[c]" : -1.0,
            "NADP[c]" : -1.0,
            "WATER[c]" : -1.0,
            "GLYCOLATE[c]" : 1.0,
            "NADPH[c]" : 1.0,
            "PROTON[c]" : 2.0
        },
        "gene_reaction_rule": "SPOA0243 or SPOA0260"
    }
]